odoo/addons/ssi_quality_control/README.rst
odoo/addons/ssi_quality_control/__init__.py
odoo/addons/ssi_quality_control/__manifest__.py
odoo/addons/ssi_quality_control/menu.xml
odoo/addons/ssi_quality_control/data/approval_template_data.xml
odoo/addons/ssi_quality_control/data/ir_sequence_data.xml
odoo/addons/ssi_quality_control/data/policy_template_data.xml
odoo/addons/ssi_quality_control/data/sequence_template_data.xml
odoo/addons/ssi_quality_control/models/__init__.py
odoo/addons/ssi_quality_control/models/mixin_qc_worksheet.py
odoo/addons/ssi_quality_control/models/qc_value_item.py
odoo/addons/ssi_quality_control/models/qc_value_set.py
odoo/addons/ssi_quality_control/models/qc_value_set_value.py
odoo/addons/ssi_quality_control/models/qc_worksheet.py
odoo/addons/ssi_quality_control/models/qc_worksheet_question.py
odoo/addons/ssi_quality_control/models/qc_worksheet_set.py
odoo/addons/ssi_quality_control/models/qc_worksheet_set_worksheet_type.py
odoo/addons/ssi_quality_control/models/qc_worksheet_type.py
odoo/addons/ssi_quality_control/models/qc_worksheet_type_question.py
odoo/addons/ssi_quality_control/models/qc_worksheet_type_question_value.py
odoo/addons/ssi_quality_control/models/res_company.py
odoo/addons/ssi_quality_control/models/res_config_settings.py
odoo/addons/ssi_quality_control/security/ir.model.access.csv
odoo/addons/ssi_quality_control/security/ir_module_category_data.xml
odoo/addons/ssi_quality_control/security/ir_rule_data.xml
odoo/addons/ssi_quality_control/security/res_group_data.xml
odoo/addons/ssi_quality_control/static/description/icon.png
odoo/addons/ssi_quality_control/static/description/risk-assessment-template.odt
odoo/addons/ssi_quality_control/templates/mixin_qc_worksheet_templates.xml
odoo/addons/ssi_quality_control/views/qc_value_item_views.xml
odoo/addons/ssi_quality_control/views/qc_value_set_views.xml
odoo/addons/ssi_quality_control/views/qc_worksheet_set_views.xml
odoo/addons/ssi_quality_control/views/qc_worksheet_type_views.xml
odoo14_addon_ssi_quality_control-14.0.2.0.0.dist-info/METADATA
odoo14_addon_ssi_quality_control-14.0.2.0.0.dist-info/WHEEL
odoo14_addon_ssi_quality_control-14.0.2.0.0.dist-info/top_level.txt
odoo14_addon_ssi_quality_control-14.0.2.0.0.dist-info/RECORD
